alertaclient/__init__.py
alertaclient/__main__.py
alertaclient/api.py
alertaclient/cli.py
alertaclient/config.py
alertaclient/exceptions.py
alertaclient/top.py
alertaclient/utils.py
alertaclient/version.py
alertaclient/auth/__init__.py
alertaclient/auth/azure.py
alertaclient/auth/github.py
alertaclient/auth/gitlab.py
alertaclient/auth/google.py
alertaclient/auth/hmac.py
alertaclient/auth/oidc.py
alertaclient/auth/token.py
alertaclient/auth/utils.py
alertaclient/commands/__init__.py
alertaclient/commands/cmd_ack.py
alertaclient/commands/cmd_action.py
alertaclient/commands/cmd_alerts.py
alertaclient/commands/cmd_blackout.py
alertaclient/commands/cmd_blackouts.py
alertaclient/commands/cmd_close.py
alertaclient/commands/cmd_config.py
alertaclient/commands/cmd_customer.py
alertaclient/commands/cmd_customers.py
alertaclient/commands/cmd_delete.py
alertaclient/commands/cmd_group.py
alertaclient/commands/cmd_groups.py
alertaclient/commands/cmd_heartbeat.py
alertaclient/commands/cmd_heartbeats.py
alertaclient/commands/cmd_help.py
alertaclient/commands/cmd_history.py
alertaclient/commands/cmd_housekeeping.py
alertaclient/commands/cmd_key.py
alertaclient/commands/cmd_keys.py
alertaclient/commands/cmd_login.py
alertaclient/commands/cmd_logout.py
alertaclient/commands/cmd_me.py
alertaclient/commands/cmd_note.py
alertaclient/commands/cmd_notes.py
alertaclient/commands/cmd_perm.py
alertaclient/commands/cmd_perms.py
alertaclient/commands/cmd_query.py
alertaclient/commands/cmd_raw.py
alertaclient/commands/cmd_revoke.py
alertaclient/commands/cmd_scopes.py
alertaclient/commands/cmd_send.py
alertaclient/commands/cmd_shelve.py
alertaclient/commands/cmd_signup.py
alertaclient/commands/cmd_status.py
alertaclient/commands/cmd_tag.py
alertaclient/commands/cmd_token.py
alertaclient/commands/cmd_top.py
alertaclient/commands/cmd_unack.py
alertaclient/commands/cmd_unshelve.py
alertaclient/commands/cmd_untag.py
alertaclient/commands/cmd_update.py
alertaclient/commands/cmd_uptime.py
alerta-8.5.3.dist-info/LICENSE
alerta-8.5.3.dist-info/METADATA
alerta-8.5.3.dist-info/NOTICE
alerta-8.5.3.dist-info/WHEEL
alerta-8.5.3.dist-info/entry_points.txt
alerta-8.5.3.dist-info/top_level.txt
alerta-8.5.3.dist-info/RECORD
