Metadata-Version: 2.1
Name: alerta
Version: 8.5.3
Summary: Alerta unified command-line tool and SDK
Home-page: https://github.com/guardian/python-alerta
Author: Nick Satterly
Author-email: nfsatterly@gmail.com
License: Apache License 2.0
Keywords: alerta client unified command line tool sdk
Classifier: Development Status :: 5 - Production/Stable
Classifier: Environment :: Console
Classifier: Intended Audience :: Information Technology
Classifier: Intended Audience :: System Administrators
Classifier: Intended Audience :: Telecommunications Industry
Classifier: License :: OSI Approved :: Apache Software License
Classifier: Programming Language :: Python :: 3.11
Classifier: Programming Language :: Python :: 3.10
Classifier: Programming Language :: Python :: 3.9
Classifier: Programming Language :: Python :: 3.8
Classifier: Topic :: System :: Monitoring
Classifier: Topic :: Software Development :: Libraries :: Python Modules
Requires-Python: >=3.8
License-File: LICENSE
License-File: NOTICE
Requires-Dist: Click
Requires-Dist: requests
Requires-Dist: requests-hawk
Requires-Dist: tabulate
Requires-Dist: pytz
